{"namedChunkGroups":{"polyfill":{"name":"polyfill","assets":[{"name":"polyfill.js","size":755575}],"filteredAssets":0,"assetsSize":755575,"filteredAuxiliaryAssets":0,"auxiliaryAssetsSize":0},"commons":{"name":"commons","assets":[{"name":"framework.js","size":2668788},{"name":"commons.css","size":3634491},{"name":"commons.js","size":2931066}],"filteredAssets":0,"assetsSize":9234345,"filteredAuxiliaryAssets":2,"auxiliaryAssetsSize":56824},"component---cache-dev-404-page-js":{"name":"component---cache-dev-404-page-js","assets":[{"name":"component---cache-dev-404-page-js.js","size":66870}],"filteredAssets":0,"assetsSize":66870,"filteredAuxiliaryAssets":0,"auxiliaryAssetsSize":0},"component---src-pages-404-js":{"name":"component---src-pages-404-js","assets":[{"name":"component---src-pages-404-js.js","size":3283617}],"filteredAssets":0,"assetsSize":3283617,"filteredAuxiliaryAssets":1,"auxiliaryAssetsSize":334115},"component---src-pages-about-js":{"name":"component---src-pages-about-js","assets":[{"name":"framework.js","size":2668788},{"name":"commons.css","size":3634491},{"name":"commons.js","size":2931066},{"name":"component---src-pages-about-js.js","size":3337093}],"filteredAssets":0,"assetsSize":12571438,"filteredAuxiliaryAssets":3,"auxiliaryAssetsSize":390939},"component---src-pages-archives-js":{"name":"component---src-pages-archives-js","assets":[{"name":"component---src-pages-archives-js.js","size":3289313}],"filteredAssets":0,"assetsSize":3289313,"filteredAuxiliaryAssets":1,"auxiliaryAssetsSize":334115},"component---src-pages-categories-js":{"name":"component---src-pages-categories-js","assets":[{"name":"component---src-pages-categories-js.js","size":3298370}],"filteredAssets":0,"assetsSize":3298370,"filteredAuxiliaryAssets":2,"auxiliaryAssetsSize":358807},"component---src-pages-index-js":{"name":"component---src-pages-index-js","assets":[{"name":"framework.js","size":2668788},{"name":"commons.css","size":3634491},{"name":"commons.js","size":2931066},{"name":"component---src-pages-index-js.js","size":3347286}],"filteredAssets":0,"assetsSize":12581631,"filteredAuxiliaryAssets":4,"auxiliaryAssetsSize":415631},"component---src-template-blog-category-js":{"name":"component---src-template-blog-category-js","assets":[{"name":"component---src-template-blog-category-js.js","size":3296388}],"filteredAssets":0,"assetsSize":3296388,"filteredAuxiliaryAssets":1,"auxiliaryAssetsSize":334115},"component---src-template-blog-template-js":{"name":"component---src-template-blog-template-js","assets":[{"name":"framework.js","size":2668788},{"name":"commons.css","size":3634491},{"name":"commons.js","size":2931066},{"name":"component---src-template-blog-template-js.js","size":3291923}],"filteredAssets":0,"assetsSize":12526268,"filteredAuxiliaryAssets":3,"auxiliaryAssetsSize":390939},"component---src-template-blogs-js":{"name":"component---src-template-blogs-js","assets":[{"name":"component---src-template-blogs-js.js","size":3295850}],"filteredAssets":0,"assetsSize":3295850,"filteredAuxiliaryAssets":1,"auxiliaryAssetsSize":334115}},"assetsByChunkName":{"polyfill":["polyfill.js"],"commons":["framework.js","commons.css","commons.js"],"component---cache-dev-404-page-js":["component---cache-dev-404-page-js.js"],"component---src-pages-404-js":["component---src-pages-404-js.js"],"component---src-pages-about-js":["framework.js","commons.css","commons.js","component---src-pages-about-js.js"],"component---src-pages-archives-js":["component---src-pages-archives-js.js"],"component---src-pages-categories-js":["component---src-pages-categories-js.js"],"component---src-pages-index-js":["framework.js","commons.css","commons.js","component---src-pages-index-js.js"],"component---src-template-blog-category-js":["component---src-template-blog-category-js.js"],"component---src-template-blog-template-js":["framework.js","commons.css","commons.js","component---src-template-blog-template-js.js"],"component---src-template-blogs-js":["component---src-template-blogs-js.js"]},"childAssetsByChunkName":{}}